<?xml version="1.0" encoding="UTF-8"?>
<!DOCTYPE ode SYSTEM "content.dtd">
<ode xmlns="http://www.intef.es/xsd/ode" version="2.0">
<userPreferences>
  <userPreference>
    <key>theme</key>
    <value>base</value>
  </userPreference>
</userPreferences>
<odeResources>
  <odeResource>
    <key>odeId</key>
    <value>20260506204724OM11NC</value>
  </odeResource>
  <odeResource>
    <key>odeVersionId</key>
    <value>2026050620472430IP6P</value>
  </odeResource>
  <odeResource>
    <key>exe_version</key>
    <value>4.0.0</value>
  </odeResource>
</odeResources>
<odeProperties>
  <odeProperty>
    <key>pp_title</key>
    <value>Proyecto VOCES QUE CUENTAN</value>
  </odeProperty>
  <odeProperty>
    <key>pp_author</key>
    <value>Gema María Ortiz López</value>
  </odeProperty>
  <odeProperty>
    <key>pp_description</key>
    <value>La situación de aprendizaje Voces que cuentan va destinada para el alumnado de 4º curso de Educación Primaria. En la que aprenderemos a conocer y manipular diferentes tipos de textos así como la creación propia de textos.</value>
  </odeProperty>
  <odeProperty>
    <key>pp_lang</key>
    <value>es</value>
  </odeProperty>
  <odeProperty>
    <key>pp_license</key>
    <value>creative commons: attribution - share alike 4.0</value>
  </odeProperty>
  <odeProperty>
    <key>pp_licenseUrl</key>
    <value>https://creativecommons.org/licenses/by-sa/4.0/</value>
  </odeProperty>
  <odeProperty>
    <key>pp_theme</key>
    <value>base</value>
  </odeProperty>
  <odeProperty>
    <key>pp_exelearning_version</key>
    <value>v4.0.0</value>
  </odeProperty>
  <odeProperty>
    <key>pp_modified</key>
    <value>1778092149086</value>
  </odeProperty>
  <odeProperty>
    <key>pp_addExeLink</key>
    <value>true</value>
  </odeProperty>
  <odeProperty>
    <key>pp_addPagination</key>
    <value>false</value>
  </odeProperty>
  <odeProperty>
    <key>pp_addSearchBox</key>
    <value>false</value>
  </odeProperty>
  <odeProperty>
    <key>pp_addAccessibilityToolbar</key>
    <value>false</value>
  </odeProperty>
  <odeProperty>
    <key>pp_addMathJax</key>
    <value>false</value>
  </odeProperty>
  <odeProperty>
    <key>exportSource</key>
    <value>true</value>
  </odeProperty>
  <odeProperty>
    <key>pp_globalFont</key>
    <value>default</value>
  </odeProperty>
</odeProperties>
<odeNavStructures>
<odeNavStructure>
  <odePageId>page-moue5mw3-e7caml6gm</odePageId>
  <odeParentPageId></odeParentPageId>
  <pageName>Comenzamos: Presentación</pageName>
  <odeNavStructureOrder>0</odeNavStructureOrder>
  <odeNavStructureProperties>
    <odeNavStructureProperty>
      <key>titlePage</key>
      <value>Comenzamos: Presentación</value>
    </odeNavStructureProperty>
    <odeNavStructureProperty>
      <key>visibility</key>
      <value>true</value>
    </odeNavStructureProperty>
    <odeNavStructureProperty>
      <key>highlight</key>
      <value>false</value>
    </odeNavStructureProperty>
    <odeNavStructureProperty>
      <key>hidePageTitle</key>
      <value>false</value>
    </odeNavStructureProperty>
    <odeNavStructureProperty>
      <key>editableInPage</key>
      <value>false</value>
    </odeNavStructureProperty>
    <odeNavStructureProperty>
      <key>titlePage</key>
      <value>Comenzamos: Presentación</value>
    </odeNavStructureProperty>
    <odeNavStructureProperty>
      <key>titleNode</key>
      <value></value>
    </odeNavStructureProperty>
  </odeNavStructureProperties>
  <odePagStructures>
    <odePagStructure>
      <odePageId>page-moue5mw3-e7caml6gm</odePageId>
      <odeBlockId>block-1778087588931-9xq53nzut</odeBlockId>
      <blockName>Descargar el archivo fuente</blockName>
      <iconName></iconName>
      <odePagStructureOrder>1</odePagStructureOrder>
      <odePagStructureProperties>
        <odePagStructureProperty>
          <key>visibility</key>
          <value>true</value>
        </odePagStructureProperty>
        <odePagStructureProperty>
          <key>teacherOnly</key>
          <value>false</value>
        </odePagStructureProperty>
        <odePagStructureProperty>
          <key>allowToggle</key>
          <value>true</value>
        </odePagStructureProperty>
        <odePagStructureProperty>
          <key>minimized</key>
          <value>false</value>
        </odePagStructureProperty>
        <odePagStructureProperty>
          <key>cssClass</key>
          <value></value>
        </odePagStructureProperty>
      </odePagStructureProperties>
      <odeComponents>
        <odeComponent>
          <odePageId>page-moue5mw3-e7caml6gm</odePageId>
          <odeBlockId>block-1778087588931-9xq53nzut</odeBlockId>
          <odeIdeviceId>idevice-1778087588929-d6z43r6o9</odeIdeviceId>
          <odeIdeviceTypeName>download-source-file</odeIdeviceTypeName>
          <htmlView><![CDATA[<div class="exe-download-package-instructions"><table class="exe-table exe-package-info"><caption title="Presentación"><a href="asset://f1e3a827-4883-3bc2-756e-6a72ee2957cb.pdf" title="Presentación">asset://f1e3a827-4883-3bc2-756e-6a72ee2957cb.pdf</a>Información general sobre este recurso educativo</caption>
<tbody>
<tr>
<th>Título</th>
<td class="mceNonEditable exe-prop-locked"><span class="exe-prop-title">Proyecto VOCES QUE CUENTAN</span></td>
</tr>
<tr>
<th>Descripción</th>
<td class="mceNonEditable exe-prop-locked"><span class="exe-prop-description">La situación de aprendizaje Voces que cuentan va destinada para el alumnado de 4º curso de Educación Primaria. En la que aprenderemos a conocer y manipular diferentes tipos de textos así como la creación propia de textos.</span></td>
</tr>
<tr>
<th>Autoría</th>
<td class="mceNonEditable exe-prop-locked"><span class="exe-prop-author">Gema María Ortiz López</span></td>
</tr>
<tr>
<th>Licencia</th>
<td class="mceNonEditable exe-prop-locked"><span class="exe-prop-license">creative commons: attribution - share alike 4.0</span></td>
</tr>
</tbody>
</table>
<p style="text-align: center;">Este contenido fue creado con <a href="https://exelearning.net/">eXeLearning</a>, el editor libre y de fuente abierta diseñado para crear recursos educativos.</p></div><p class="exe-download-package-link"><a download="exe-package:elp-name" href="exe-package:elp" style="background-color:#107275;color:#ffffff;">Descargar el archivo .elpx</a></p>]]></htmlView>
          <jsonProperties></jsonProperties>
          <odeComponentsOrder>0</odeComponentsOrder>
          <odeComponentsProperties>
            <odeComponentsProperty>
              <key>visibility</key>
              <value>true</value>
            </odeComponentsProperty>
            <odeComponentsProperty>
              <key>teacherOnly</key>
              <value>false</value>
            </odeComponentsProperty>
            <odeComponentsProperty>
              <key>cssClass</key>
              <value></value>
            </odeComponentsProperty>
          </odeComponentsProperties>
        </odeComponent>
      </odeComponents>
    </odePagStructure>
  </odePagStructures>
</odeNavStructure>
<odeNavStructure>
  <odePageId>page-moue5mw5-4l4hcscza</odePageId>
  <odeParentPageId></odeParentPageId>
  <pageName>sesión 1: Licencias y seguridad</pageName>
  <odeNavStructureOrder>1</odeNavStructureOrder>
  <odeNavStructureProperties>
    <odeNavStructureProperty>
      <key>titlePage</key>
      <value>sesión 1: Licencias y seguridad</value>
    </odeNavStructureProperty>
    <odeNavStructureProperty>
      <key>visibility</key>
      <value>true</value>
    </odeNavStructureProperty>
    <odeNavStructureProperty>
      <key>highlight</key>
      <value>false</value>
    </odeNavStructureProperty>
    <odeNavStructureProperty>
      <key>hidePageTitle</key>
      <value>false</value>
    </odeNavStructureProperty>
    <odeNavStructureProperty>
      <key>editableInPage</key>
      <value>false</value>
    </odeNavStructureProperty>
    <odeNavStructureProperty>
      <key>titlePage</key>
      <value>sesión 1</value>
    </odeNavStructureProperty>
    <odeNavStructureProperty>
      <key>titleNode</key>
      <value>sesión 1: Licencias y seguridad</value>
    </odeNavStructureProperty>
  </odeNavStructureProperties>
  <odePagStructures>
    <odePagStructure>
      <odePageId>page-moue5mw5-4l4hcscza</odePageId>
      <odeBlockId>block-1778087871215-frga0xsc8</odeBlockId>
      <blockName>Descargar el archivo fuente</blockName>
      <iconName></iconName>
      <odePagStructureOrder>1</odePagStructureOrder>
      <odePagStructureProperties>
        <odePagStructureProperty>
          <key>visibility</key>
          <value>true</value>
        </odePagStructureProperty>
        <odePagStructureProperty>
          <key>teacherOnly</key>
          <value>false</value>
        </odePagStructureProperty>
        <odePagStructureProperty>
          <key>allowToggle</key>
          <value>true</value>
        </odePagStructureProperty>
        <odePagStructureProperty>
          <key>minimized</key>
          <value>false</value>
        </odePagStructureProperty>
        <odePagStructureProperty>
          <key>cssClass</key>
          <value></value>
        </odePagStructureProperty>
      </odePagStructureProperties>
      <odeComponents>
        <odeComponent>
          <odePageId>page-moue5mw5-4l4hcscza</odePageId>
          <odeBlockId>block-1778087871215-frga0xsc8</odeBlockId>
          <odeIdeviceId>idevice-1778087871212-g9b13zpms</odeIdeviceId>
          <odeIdeviceTypeName>download-source-file</odeIdeviceTypeName>
          <htmlView><![CDATA[<div class="exe-download-package-instructions"><table class="exe-table exe-package-info"><caption title="2.3.pdf"><a href="asset://86a4712a-c12d-6564-3ba5-7eda3d26b782.pdf" title="2.3.pdf">asset://86a4712a-c12d-6564-3ba5-7eda3d26b782.pdf</a>Información general sobre este recurso educativo</caption>
<tbody>
<tr>
<th>Título</th>
<td class="mceNonEditable exe-prop-locked"><span class="exe-prop-title">Proyecto VOCES QUE CUENTAN</span></td>
</tr>
<tr>
<th>Descripción</th>
<td class="mceNonEditable exe-prop-locked"><span class="exe-prop-description">La situación de aprendizaje Voces que cuentan va destinada para el alumnado de 4º curso de Educación Primaria. En la que aprenderemos a conocer y manipular diferentes tipos de textos así como la creación propia de textos.</span></td>
</tr>
<tr>
<th>Autoría</th>
<td class="mceNonEditable exe-prop-locked"><span class="exe-prop-author">Gema María Ortiz López</span></td>
</tr>
<tr>
<th>Licencia</th>
<td class="mceNonEditable exe-prop-locked"><span class="exe-prop-license">creative commons: attribution - share alike 4.0</span></td>
</tr>
</tbody>
</table>
<p style="text-align: center;">Este contenido fue creado con <a href="https://exelearning.net/">eXeLearning</a>, el editor libre y de fuente abierta diseñado para crear recursos educativos.</p></div><p class="exe-download-package-link"><a download="exe-package:elp-name" href="exe-package:elp" style="background-color:#107275;color:#ffffff;">Descargar el archivo .elpx</a></p>]]></htmlView>
          <jsonProperties></jsonProperties>
          <odeComponentsOrder>0</odeComponentsOrder>
          <odeComponentsProperties>
            <odeComponentsProperty>
              <key>visibility</key>
              <value>true</value>
            </odeComponentsProperty>
            <odeComponentsProperty>
              <key>teacherOnly</key>
              <value>false</value>
            </odeComponentsProperty>
            <odeComponentsProperty>
              <key>cssClass</key>
              <value></value>
            </odeComponentsProperty>
          </odeComponentsProperties>
        </odeComponent>
      </odeComponents>
    </odePagStructure>
  </odePagStructures>
</odeNavStructure>
<odeNavStructure>
  <odePageId>page-moue5mw6-c9dob3bg0</odePageId>
  <odeParentPageId></odeParentPageId>
  <pageName>Curación de contenido</pageName>
  <odeNavStructureOrder>2</odeNavStructureOrder>
  <odeNavStructureProperties>
    <odeNavStructureProperty>
      <key>titlePage</key>
      <value>Curación de contenido</value>
    </odeNavStructureProperty>
    <odeNavStructureProperty>
      <key>visibility</key>
      <value>true</value>
    </odeNavStructureProperty>
    <odeNavStructureProperty>
      <key>highlight</key>
      <value>false</value>
    </odeNavStructureProperty>
    <odeNavStructureProperty>
      <key>hidePageTitle</key>
      <value>false</value>
    </odeNavStructureProperty>
    <odeNavStructureProperty>
      <key>editableInPage</key>
      <value>false</value>
    </odeNavStructureProperty>
    <odeNavStructureProperty>
      <key>titlePage</key>
      <value>Curación de contenido</value>
    </odeNavStructureProperty>
    <odeNavStructureProperty>
      <key>titleNode</key>
      <value></value>
    </odeNavStructureProperty>
  </odeNavStructureProperties>
  <odePagStructures>
    <odePagStructure>
      <odePageId>page-moue5mw6-c9dob3bg0</odePageId>
      <odeBlockId>block-1778088060920-om0n1kwe5</odeBlockId>
      <blockName>Descargar el archivo fuente</blockName>
      <iconName></iconName>
      <odePagStructureOrder>1</odePagStructureOrder>
      <odePagStructureProperties>
        <odePagStructureProperty>
          <key>visibility</key>
          <value>true</value>
        </odePagStructureProperty>
        <odePagStructureProperty>
          <key>teacherOnly</key>
          <value>false</value>
        </odePagStructureProperty>
        <odePagStructureProperty>
          <key>allowToggle</key>
          <value>true</value>
        </odePagStructureProperty>
        <odePagStructureProperty>
          <key>minimized</key>
          <value>false</value>
        </odePagStructureProperty>
        <odePagStructureProperty>
          <key>cssClass</key>
          <value></value>
        </odePagStructureProperty>
      </odePagStructureProperties>
      <odeComponents>
        <odeComponent>
          <odePageId>page-moue5mw6-c9dob3bg0</odePageId>
          <odeBlockId>block-1778088060920-om0n1kwe5</odeBlockId>
          <odeIdeviceId>idevice-1778088060917-qrvl8sj53</odeIdeviceId>
          <odeIdeviceTypeName>download-source-file</odeIdeviceTypeName>
          <htmlView><![CDATA[<div class="exe-download-package-instructions"><table class="exe-table exe-package-info"><caption title=""><a href="https://padlet.com/ceipgemasevilla/grafico-mapa-conceptual-esquema-ideas-creativo-original-mult-ua15nneeiuziilr?frame_id=page%3Am4jA538DnDb_4Y5iJqv2x">https://padlet.com/ceipgemasevilla/grafico-mapa-conceptual-esquema-ideas-creativo-original-mult-ua15nneeiuziilr?frame_id=page%3Am4jA538DnDb_4Y5iJqv2x</a>Información general sobre este recurso educativo</caption>
<tbody>
<tr>
<th>Título</th>
<td class="mceNonEditable exe-prop-locked"><span class="exe-prop-title">Proyecto VOCES QUE CUENTAN</span></td>
</tr>
<tr>
<th>Descripción</th>
<td class="mceNonEditable exe-prop-locked"><span class="exe-prop-description">La situación de aprendizaje Voces que cuentan va destinada para el alumnado de 4º curso de Educación Primaria. En la que aprenderemos a conocer y manipular diferentes tipos de textos así como la creación propia de textos.</span></td>
</tr>
<tr>
<th>Autoría</th>
<td class="mceNonEditable exe-prop-locked"><span class="exe-prop-author">Gema María Ortiz López</span></td>
</tr>
<tr>
<th>Licencia</th>
<td class="mceNonEditable exe-prop-locked"><span class="exe-prop-license">creative commons: attribution - share alike 4.0</span></td>
</tr>
</tbody>
</table>
<p style="text-align: center;">Este contenido fue creado con <a href="https://exelearning.net/">eXeLearning</a>, el editor libre y de fuente abierta diseñado para crear recursos educativos.</p></div><p class="exe-download-package-link"><a download="exe-package:elp-name" href="exe-package:elp" style="background-color:#107275;color:#ffffff;">Descargar el archivo .elpx</a></p>]]></htmlView>
          <jsonProperties></jsonProperties>
          <odeComponentsOrder>0</odeComponentsOrder>
          <odeComponentsProperties>
            <odeComponentsProperty>
              <key>visibility</key>
              <value>true</value>
            </odeComponentsProperty>
            <odeComponentsProperty>
              <key>teacherOnly</key>
              <value>false</value>
            </odeComponentsProperty>
            <odeComponentsProperty>
              <key>cssClass</key>
              <value></value>
            </odeComponentsProperty>
          </odeComponentsProperties>
        </odeComponent>
      </odeComponents>
    </odePagStructure>
    <odePagStructure>
      <odePageId>page-moue5mw6-c9dob3bg0</odePageId>
      <odeBlockId>block-1778088135155-2260ytc9p</odeBlockId>
      <blockName>Descargar el archivo fuente</blockName>
      <iconName></iconName>
      <odePagStructureOrder>1</odePagStructureOrder>
      <odePagStructureProperties>
        <odePagStructureProperty>
          <key>visibility</key>
          <value>true</value>
        </odePagStructureProperty>
        <odePagStructureProperty>
          <key>teacherOnly</key>
          <value>false</value>
        </odePagStructureProperty>
        <odePagStructureProperty>
          <key>allowToggle</key>
          <value>true</value>
        </odePagStructureProperty>
        <odePagStructureProperty>
          <key>minimized</key>
          <value>false</value>
        </odePagStructureProperty>
        <odePagStructureProperty>
          <key>cssClass</key>
          <value></value>
        </odePagStructureProperty>
      </odePagStructureProperties>
      <odeComponents>
        <odeComponent>
          <odePageId>page-moue5mw6-c9dob3bg0</odePageId>
          <odeBlockId>block-1778088135155-2260ytc9p</odeBlockId>
          <odeIdeviceId>idevice-1778088135153-855wx8dxv</odeIdeviceId>
          <odeIdeviceTypeName>download-source-file</odeIdeviceTypeName>
          <htmlView><![CDATA[<div class="exe-download-package-instructions"><table class="exe-table exe-package-info"><caption title=""><a href="https://www.symbaloo.com/shared/AAAAAbXgvccAA41-5EN5Qg==">https://www.symbaloo.com/shared/AAAAAbXgvccAA41-5EN5Qg==</a>Información general sobre este recurso educativo</caption>
<tbody>
<tr>
<th>Título</th>
<td class="mceNonEditable exe-prop-locked"><span class="exe-prop-title">Proyecto VOCES QUE CUENTAN</span></td>
</tr>
<tr>
<th>Descripción</th>
<td class="mceNonEditable exe-prop-locked"><span class="exe-prop-description">La situación de aprendizaje Voces que cuentan va destinada para el alumnado de 4º curso de Educación Primaria. En la que aprenderemos a conocer y manipular diferentes tipos de textos así como la creación propia de textos.</span></td>
</tr>
<tr>
<th>Autoría</th>
<td class="mceNonEditable exe-prop-locked"><span class="exe-prop-author">Gema María Ortiz López</span></td>
</tr>
<tr>
<th>Licencia</th>
<td class="mceNonEditable exe-prop-locked"><span class="exe-prop-license">creative commons: attribution - share alike 4.0</span></td>
</tr>
</tbody>
</table>
<p style="text-align: center;">Este contenido fue creado con <a href="https://exelearning.net/">eXeLearning</a>, el editor libre y de fuente abierta diseñado para crear recursos educativos.</p></div><p class="exe-download-package-link"><a download="exe-package:elp-name" href="exe-package:elp" style="background-color:#107275;color:#ffffff;">Descargar el archivo .elpx</a></p>]]></htmlView>
          <jsonProperties></jsonProperties>
          <odeComponentsOrder>0</odeComponentsOrder>
          <odeComponentsProperties>
            <odeComponentsProperty>
              <key>visibility</key>
              <value>true</value>
            </odeComponentsProperty>
            <odeComponentsProperty>
              <key>teacherOnly</key>
              <value>false</value>
            </odeComponentsProperty>
            <odeComponentsProperty>
              <key>cssClass</key>
              <value></value>
            </odeComponentsProperty>
          </odeComponentsProperties>
        </odeComponent>
      </odeComponents>
    </odePagStructure>
  </odePagStructures>
</odeNavStructure>
<odeNavStructure>
  <odePageId>page-moue5mw8-1179fwth1</odePageId>
  <odeParentPageId></odeParentPageId>
  <pageName>ACTIVIDADES</pageName>
  <odeNavStructureOrder>3</odeNavStructureOrder>
  <odeNavStructureProperties>
    <odeNavStructureProperty>
      <key>titlePage</key>
      <value>ACTIVIDADES</value>
    </odeNavStructureProperty>
    <odeNavStructureProperty>
      <key>visibility</key>
      <value>true</value>
    </odeNavStructureProperty>
    <odeNavStructureProperty>
      <key>highlight</key>
      <value>false</value>
    </odeNavStructureProperty>
    <odeNavStructureProperty>
      <key>hidePageTitle</key>
      <value>false</value>
    </odeNavStructureProperty>
    <odeNavStructureProperty>
      <key>editableInPage</key>
      <value>false</value>
    </odeNavStructureProperty>
    <odeNavStructureProperty>
      <key>titlePage</key>
      <value>ACTIVIDADES</value>
    </odeNavStructureProperty>
    <odeNavStructureProperty>
      <key>titleNode</key>
      <value></value>
    </odeNavStructureProperty>
  </odeNavStructureProperties>
  <odePagStructures>
  </odePagStructures>
</odeNavStructure>
<odeNavStructure>
  <odePageId>page-moue5mwb-hvgce3q5e</odePageId>
  <odeParentPageId>page-moue5mw8-1179fwth1</odeParentPageId>
  <pageName>Tarea 1</pageName>
  <odeNavStructureOrder>0</odeNavStructureOrder>
  <odeNavStructureProperties>
    <odeNavStructureProperty>
      <key>titlePage</key>
      <value>Tarea 1</value>
    </odeNavStructureProperty>
    <odeNavStructureProperty>
      <key>visibility</key>
      <value>true</value>
    </odeNavStructureProperty>
    <odeNavStructureProperty>
      <key>highlight</key>
      <value>false</value>
    </odeNavStructureProperty>
    <odeNavStructureProperty>
      <key>hidePageTitle</key>
      <value>false</value>
    </odeNavStructureProperty>
    <odeNavStructureProperty>
      <key>editableInPage</key>
      <value>false</value>
    </odeNavStructureProperty>
    <odeNavStructureProperty>
      <key>titlePage</key>
      <value>Tarea 1</value>
    </odeNavStructureProperty>
    <odeNavStructureProperty>
      <key>titleNode</key>
      <value></value>
    </odeNavStructureProperty>
  </odeNavStructureProperties>
  <odePagStructures>
    <odePagStructure>
      <odePageId>page-moue5mwb-hvgce3q5e</odePageId>
      <odeBlockId>block-1778088485597-zwrw2zzjd</odeBlockId>
      <blockName>Texto</blockName>
      <iconName></iconName>
      <odePagStructureOrder>1</odePagStructureOrder>
      <odePagStructureProperties>
        <odePagStructureProperty>
          <key>visibility</key>
          <value>true</value>
        </odePagStructureProperty>
        <odePagStructureProperty>
          <key>teacherOnly</key>
          <value>false</value>
        </odePagStructureProperty>
        <odePagStructureProperty>
          <key>allowToggle</key>
          <value>true</value>
        </odePagStructureProperty>
        <odePagStructureProperty>
          <key>minimized</key>
          <value>false</value>
        </odePagStructureProperty>
        <odePagStructureProperty>
          <key>cssClass</key>
          <value></value>
        </odePagStructureProperty>
      </odePagStructureProperties>
      <odeComponents>
        <odeComponent>
          <odePageId>page-moue5mwb-hvgce3q5e</odePageId>
          <odeBlockId>block-1778088485597-zwrw2zzjd</odeBlockId>
          <odeIdeviceId>idevice-1778088485594-h4tnsksfj</odeIdeviceId>
          <odeIdeviceTypeName>text</odeIdeviceTypeName>
          <htmlView><![CDATA[<div class="exe-text-template">
    <p>1.Activación de conocimientos/ ideas previas, lluvia de ideas. ¿Qué sabemos acerca de los diferentes tipos de texto? ¿Cuántos conocéis?</p>
<p>Asociada a criterio de evaluación: CE3.1 Participar en interacciones comunicativas.</p>
</div>]]></htmlView>
          <jsonProperties><![CDATA[{"ideviceId":"idevice-1778088485594-h4tnsksfj","textInfoDurationInput":"","textInfoDurationTextInput":"Duración","textInfoParticipantsInput":"","textInfoParticipantsTextInput":"Agrupamiento","textTextarea":"<p>1.Activación de conocimientos/ ideas previas, lluvia de ideas. ¿Qué sabemos acerca de los diferentes tipos de texto? ¿Cuántos conocéis?</p>\n<p>Asociada a criterio de evaluación: CE3.1 Participar en interacciones comunicativas.</p>","textFeedbackInput":"Mostrar retroalimentación","textFeedbackTextarea":""}]]></jsonProperties>
          <odeComponentsOrder>0</odeComponentsOrder>
          <odeComponentsProperties>
            <odeComponentsProperty>
              <key>visibility</key>
              <value>true</value>
            </odeComponentsProperty>
            <odeComponentsProperty>
              <key>teacherOnly</key>
              <value>false</value>
            </odeComponentsProperty>
            <odeComponentsProperty>
              <key>cssClass</key>
              <value></value>
            </odeComponentsProperty>
          </odeComponentsProperties>
        </odeComponent>
      </odeComponents>
    </odePagStructure>
  </odePagStructures>
</odeNavStructure>
<odeNavStructure>
  <odePageId>page-moue5mwd-qiia6fro9</odePageId>
  <odeParentPageId>page-moue5mw8-1179fwth1</odeParentPageId>
  <pageName>Tarea 2</pageName>
  <odeNavStructureOrder>1</odeNavStructureOrder>
  <odeNavStructureProperties>
    <odeNavStructureProperty>
      <key>titlePage</key>
      <value>Tarea 2</value>
    </odeNavStructureProperty>
    <odeNavStructureProperty>
      <key>visibility</key>
      <value>true</value>
    </odeNavStructureProperty>
    <odeNavStructureProperty>
      <key>highlight</key>
      <value>false</value>
    </odeNavStructureProperty>
    <odeNavStructureProperty>
      <key>hidePageTitle</key>
      <value>false</value>
    </odeNavStructureProperty>
    <odeNavStructureProperty>
      <key>editableInPage</key>
      <value>false</value>
    </odeNavStructureProperty>
    <odeNavStructureProperty>
      <key>titlePage</key>
      <value>Tarea 2</value>
    </odeNavStructureProperty>
    <odeNavStructureProperty>
      <key>titleNode</key>
      <value></value>
    </odeNavStructureProperty>
  </odeNavStructureProperties>
  <odePagStructures>
    <odePagStructure>
      <odePageId>page-moue5mwd-qiia6fro9</odePageId>
      <odeBlockId>block-1778088758682-5popp5rmz</odeBlockId>
      <blockName>Texto</blockName>
      <iconName></iconName>
      <odePagStructureOrder>1</odePagStructureOrder>
      <odePagStructureProperties>
        <odePagStructureProperty>
          <key>visibility</key>
          <value>true</value>
        </odePagStructureProperty>
        <odePagStructureProperty>
          <key>teacherOnly</key>
          <value>false</value>
        </odePagStructureProperty>
        <odePagStructureProperty>
          <key>allowToggle</key>
          <value>true</value>
        </odePagStructureProperty>
        <odePagStructureProperty>
          <key>minimized</key>
          <value>false</value>
        </odePagStructureProperty>
        <odePagStructureProperty>
          <key>cssClass</key>
          <value></value>
        </odePagStructureProperty>
      </odePagStructureProperties>
      <odeComponents>
        <odeComponent>
          <odePageId>page-moue5mwd-qiia6fro9</odePageId>
          <odeBlockId>block-1778088758682-5popp5rmz</odeBlockId>
          <odeIdeviceId>idevice-1778088758675-u7ym2a8b6</odeIdeviceId>
          <odeIdeviceTypeName>text</odeIdeviceTypeName>
          <htmlView><![CDATA[<div class="exe-text-template">
    <p>2. Se muestran diferentes tipos de texto y deben identificar de qué tipo de texto se trata.</p>
<p>Asociada a criterios de evaluación: CE1.1 Comprender el sentido global de textos orales y escritos. CE1.2 Identificar la tipología textual y su finalidad.<a href="asset://aed47b64-8610-7ca1-dbb7-23f8be581c05.pdf" title="tarea identifica diferentes textos.pdf">asset://aed47b64-8610-7ca1-dbb7-23f8be581c05.pdf</a></p>
</div>]]></htmlView>
          <jsonProperties><![CDATA[{"ideviceId":"idevice-1778088758675-u7ym2a8b6","textInfoDurationInput":"","textInfoDurationTextInput":"Duración","textInfoParticipantsInput":"","textInfoParticipantsTextInput":"Agrupamiento","textTextarea":"<p>2. Se muestran diferentes tipos de texto y deben identificar de qué tipo de texto se trata.</p>\n<p>Asociada a criterios de evaluación: CE1.1 Comprender el sentido global de textos orales y escritos. CE1.2 Identificar la tipología textual y su finalidad.<a href=\"asset://aed47b64-8610-7ca1-dbb7-23f8be581c05.pdf\" title=\"tarea identifica diferentes textos.pdf\">asset://aed47b64-8610-7ca1-dbb7-23f8be581c05.pdf</a></p>","textFeedbackInput":"Mostrar retroalimentación","textFeedbackTextarea":""}]]></jsonProperties>
          <odeComponentsOrder>0</odeComponentsOrder>
          <odeComponentsProperties>
            <odeComponentsProperty>
              <key>visibility</key>
              <value>true</value>
            </odeComponentsProperty>
            <odeComponentsProperty>
              <key>teacherOnly</key>
              <value>false</value>
            </odeComponentsProperty>
            <odeComponentsProperty>
              <key>cssClass</key>
              <value></value>
            </odeComponentsProperty>
          </odeComponentsProperties>
        </odeComponent>
      </odeComponents>
    </odePagStructure>
  </odePagStructures>
</odeNavStructure>
<odeNavStructure>
  <odePageId>page-moue5mwe-6umrts728</odePageId>
  <odeParentPageId>page-moue5mw8-1179fwth1</odeParentPageId>
  <pageName>Tarea 3</pageName>
  <odeNavStructureOrder>2</odeNavStructureOrder>
  <odeNavStructureProperties>
    <odeNavStructureProperty>
      <key>titlePage</key>
      <value>Tarea 3</value>
    </odeNavStructureProperty>
    <odeNavStructureProperty>
      <key>visibility</key>
      <value>true</value>
    </odeNavStructureProperty>
    <odeNavStructureProperty>
      <key>highlight</key>
      <value>false</value>
    </odeNavStructureProperty>
    <odeNavStructureProperty>
      <key>hidePageTitle</key>
      <value>false</value>
    </odeNavStructureProperty>
    <odeNavStructureProperty>
      <key>editableInPage</key>
      <value>false</value>
    </odeNavStructureProperty>
    <odeNavStructureProperty>
      <key>titlePage</key>
      <value>Tarea 3</value>
    </odeNavStructureProperty>
    <odeNavStructureProperty>
      <key>titleNode</key>
      <value></value>
    </odeNavStructureProperty>
  </odeNavStructureProperties>
  <odePagStructures>
    <odePagStructure>
      <odePageId>page-moue5mwe-6umrts728</odePageId>
      <odeBlockId>block-1778089751735-qdmmusx3t</odeBlockId>
      <blockName>Texto</blockName>
      <iconName></iconName>
      <odePagStructureOrder>1</odePagStructureOrder>
      <odePagStructureProperties>
        <odePagStructureProperty>
          <key>visibility</key>
          <value>true</value>
        </odePagStructureProperty>
        <odePagStructureProperty>
          <key>teacherOnly</key>
          <value>false</value>
        </odePagStructureProperty>
        <odePagStructureProperty>
          <key>allowToggle</key>
          <value>true</value>
        </odePagStructureProperty>
        <odePagStructureProperty>
          <key>minimized</key>
          <value>false</value>
        </odePagStructureProperty>
        <odePagStructureProperty>
          <key>cssClass</key>
          <value></value>
        </odePagStructureProperty>
      </odePagStructureProperties>
      <odeComponents>
        <odeComponent>
          <odePageId>page-moue5mwe-6umrts728</odePageId>
          <odeBlockId>block-1778089751735-qdmmusx3t</odeBlockId>
          <odeIdeviceId>idevice-1778089751727-f9o7h5pld</odeIdeviceId>
          <odeIdeviceTypeName>text</odeIdeviceTypeName>
          <htmlView><![CDATA[<div class="exe-text-template">
    <p>3. Detectives de textos. Leeré pistas. El alumnado debe adivinar el tipo de texto.</p>
<p>Asociada a criterios de evaluación: CE1.1 Comprender el sentido global de textos orales y escritos. CE1.2 Identificar la tipología textual y su finalidad. <a href="asset://0015bd25-9814-88a7-6967-d849a689824c.pdf" title="Detectives de textos.pdf">asset://0015bd25-9814-88a7-6967-d849a689824c.pdf</a></p>
</div>]]></htmlView>
          <jsonProperties><![CDATA[{"ideviceId":"idevice-1778089751727-f9o7h5pld","textInfoDurationInput":"","textInfoDurationTextInput":"Duración","textInfoParticipantsInput":"","textInfoParticipantsTextInput":"Agrupamiento","textTextarea":"<p>3. Detectives de textos. Leeré pistas. El alumnado debe adivinar el tipo de texto.</p>\n<p>Asociada a criterios de evaluación: CE1.1 Comprender el sentido global de textos orales y escritos. CE1.2 Identificar la tipología textual y su finalidad. <a href=\"asset://0015bd25-9814-88a7-6967-d849a689824c.pdf\" title=\"Detectives de textos.pdf\">asset://0015bd25-9814-88a7-6967-d849a689824c.pdf</a></p>","textFeedbackInput":"Mostrar retroalimentación","textFeedbackTextarea":""}]]></jsonProperties>
          <odeComponentsOrder>0</odeComponentsOrder>
          <odeComponentsProperties>
            <odeComponentsProperty>
              <key>visibility</key>
              <value>true</value>
            </odeComponentsProperty>
            <odeComponentsProperty>
              <key>teacherOnly</key>
              <value>false</value>
            </odeComponentsProperty>
            <odeComponentsProperty>
              <key>cssClass</key>
              <value></value>
            </odeComponentsProperty>
          </odeComponentsProperties>
        </odeComponent>
      </odeComponents>
    </odePagStructure>
  </odePagStructures>
</odeNavStructure>
<odeNavStructure>
  <odePageId>page-moue5mwe-rrekx65ha</odePageId>
  <odeParentPageId>page-moue5mw8-1179fwth1</odeParentPageId>
  <pageName>Tarea 4</pageName>
  <odeNavStructureOrder>3</odeNavStructureOrder>
  <odeNavStructureProperties>
    <odeNavStructureProperty>
      <key>titlePage</key>
      <value>Tarea 4</value>
    </odeNavStructureProperty>
    <odeNavStructureProperty>
      <key>visibility</key>
      <value>true</value>
    </odeNavStructureProperty>
    <odeNavStructureProperty>
      <key>highlight</key>
      <value>false</value>
    </odeNavStructureProperty>
    <odeNavStructureProperty>
      <key>hidePageTitle</key>
      <value>false</value>
    </odeNavStructureProperty>
    <odeNavStructureProperty>
      <key>editableInPage</key>
      <value>false</value>
    </odeNavStructureProperty>
    <odeNavStructureProperty>
      <key>titlePage</key>
      <value>Tarea 4</value>
    </odeNavStructureProperty>
    <odeNavStructureProperty>
      <key>titleNode</key>
      <value></value>
    </odeNavStructureProperty>
  </odeNavStructureProperties>
  <odePagStructures>
    <odePagStructure>
      <odePageId>page-moue5mwe-rrekx65ha</odePageId>
      <odeBlockId>block-1778091019689-1zbcg2d2m</odeBlockId>
      <blockName>Texto</blockName>
      <iconName></iconName>
      <odePagStructureOrder>1</odePagStructureOrder>
      <odePagStructureProperties>
        <odePagStructureProperty>
          <key>visibility</key>
          <value>true</value>
        </odePagStructureProperty>
        <odePagStructureProperty>
          <key>teacherOnly</key>
          <value>false</value>
        </odePagStructureProperty>
        <odePagStructureProperty>
          <key>allowToggle</key>
          <value>true</value>
        </odePagStructureProperty>
        <odePagStructureProperty>
          <key>minimized</key>
          <value>false</value>
        </odePagStructureProperty>
        <odePagStructureProperty>
          <key>cssClass</key>
          <value></value>
        </odePagStructureProperty>
      </odePagStructureProperties>
      <odeComponents>
        <odeComponent>
          <odePageId>page-moue5mwe-rrekx65ha</odePageId>
          <odeBlockId>block-1778091019689-1zbcg2d2m</odeBlockId>
          <odeIdeviceId>idevice-1778091019682-v0wzpb6mh</odeIdeviceId>
          <odeIdeviceTypeName>text</odeIdeviceTypeName>
          <htmlView><![CDATA[<div class="exe-text-template">
    <p>Cada alumno y alumna elaborará su propio cuento creativo. Este texto formará parte del producto final “Voces que cuentan”, que será publicado en formato digital (libro)</p>
<p>Criterios de evaluación: CE1.2 → Extrae ideas principales CE2.1 → Produce textos coherentes y estructurados CE2.2 → Aplica ortografía básica (mayúsculas, puntuación) CE3.1 → Participa en intercambios comunicativos CE4.1 → Usa herramientas digitales para crear contenido.<a href="asset://4213b092-760d-cb77-4e17-7a7347a79d69.pdf" title="Fabrica de cuentos.pdf">asset://4213b092-760d-cb77-4e17-7a7347a79d69.pdf</a></p>
</div>]]></htmlView>
          <jsonProperties><![CDATA[{"ideviceId":"idevice-1778091019682-v0wzpb6mh","textInfoDurationInput":"","textInfoDurationTextInput":"Duración","textInfoParticipantsInput":"","textInfoParticipantsTextInput":"Agrupamiento","textTextarea":"<p>Cada alumno y alumna elaborará su propio cuento creativo. Este texto formará parte del producto final “Voces que cuentan”, que será publicado en formato digital (libro)</p>\n<p>Criterios de evaluación: CE1.2 → Extrae ideas principales CE2.1 → Produce textos coherentes y estructurados CE2.2 → Aplica ortografía básica (mayúsculas, puntuación) CE3.1 → Participa en intercambios comunicativos CE4.1 → Usa herramientas digitales para crear contenido.<a href=\"asset://4213b092-760d-cb77-4e17-7a7347a79d69.pdf\" title=\"Fabrica de cuentos.pdf\">asset://4213b092-760d-cb77-4e17-7a7347a79d69.pdf</a></p>","textFeedbackInput":"Mostrar retroalimentación","textFeedbackTextarea":""}]]></jsonProperties>
          <odeComponentsOrder>0</odeComponentsOrder>
          <odeComponentsProperties>
            <odeComponentsProperty>
              <key>visibility</key>
              <value>true</value>
            </odeComponentsProperty>
            <odeComponentsProperty>
              <key>teacherOnly</key>
              <value>false</value>
            </odeComponentsProperty>
            <odeComponentsProperty>
              <key>cssClass</key>
              <value></value>
            </odeComponentsProperty>
          </odeComponentsProperties>
        </odeComponent>
      </odeComponents>
    </odePagStructure>
  </odePagStructures>
</odeNavStructure>
<odeNavStructure>
  <odePageId>page-moue5mwf-hqo29ye42</odePageId>
  <odeParentPageId>page-moue5mw8-1179fwth1</odeParentPageId>
  <pageName>Tarea 5</pageName>
  <odeNavStructureOrder>4</odeNavStructureOrder>
  <odeNavStructureProperties>
    <odeNavStructureProperty>
      <key>titlePage</key>
      <value>Tarea 5</value>
    </odeNavStructureProperty>
    <odeNavStructureProperty>
      <key>visibility</key>
      <value>true</value>
    </odeNavStructureProperty>
    <odeNavStructureProperty>
      <key>highlight</key>
      <value>false</value>
    </odeNavStructureProperty>
    <odeNavStructureProperty>
      <key>hidePageTitle</key>
      <value>false</value>
    </odeNavStructureProperty>
    <odeNavStructureProperty>
      <key>editableInPage</key>
      <value>false</value>
    </odeNavStructureProperty>
    <odeNavStructureProperty>
      <key>titlePage</key>
      <value>Tarea 5</value>
    </odeNavStructureProperty>
    <odeNavStructureProperty>
      <key>titleNode</key>
      <value></value>
    </odeNavStructureProperty>
  </odeNavStructureProperties>
  <odePagStructures>
    <odePagStructure>
      <odePageId>page-moue5mwf-hqo29ye42</odePageId>
      <odeBlockId>block-1778091631313-qbjp58bks</odeBlockId>
      <blockName>Texto</blockName>
      <iconName></iconName>
      <odePagStructureOrder>1</odePagStructureOrder>
      <odePagStructureProperties>
        <odePagStructureProperty>
          <key>visibility</key>
          <value>true</value>
        </odePagStructureProperty>
        <odePagStructureProperty>
          <key>teacherOnly</key>
          <value>false</value>
        </odePagStructureProperty>
        <odePagStructureProperty>
          <key>allowToggle</key>
          <value>true</value>
        </odePagStructureProperty>
        <odePagStructureProperty>
          <key>minimized</key>
          <value>false</value>
        </odePagStructureProperty>
        <odePagStructureProperty>
          <key>cssClass</key>
          <value></value>
        </odePagStructureProperty>
      </odePagStructureProperties>
      <odeComponents>
        <odeComponent>
          <odePageId>page-moue5mwf-hqo29ye42</odePageId>
          <odeBlockId>block-1778091631313-qbjp58bks</odeBlockId>
          <odeIdeviceId>idevice-1778091631310-qsbid7blq</odeIdeviceId>
          <odeIdeviceTypeName>text</odeIdeviceTypeName>
          <htmlView><![CDATA[<div class="exe-text-template">
    <p>Exposición oral. Cada alumno contará su cuento al resto de la clase de forma oral.</p>
<p>Criterios de evaluación: CE2.1 → Produce textos coherentes y estructurados CE3.1 → Participa en intercambios comunicativos</p>
</div>]]></htmlView>
          <jsonProperties><![CDATA[{"ideviceId":"idevice-1778091631310-qsbid7blq","textInfoDurationInput":"","textInfoDurationTextInput":"Duración","textInfoParticipantsInput":"","textInfoParticipantsTextInput":"Agrupamiento","textTextarea":"<p>Exposición oral. Cada alumno contará su cuento al resto de la clase de forma oral.</p>\n<p>Criterios de evaluación: CE2.1 → Produce textos coherentes y estructurados CE3.1 → Participa en intercambios comunicativos</p>","textFeedbackInput":"Mostrar retroalimentación","textFeedbackTextarea":""}]]></jsonProperties>
          <odeComponentsOrder>0</odeComponentsOrder>
          <odeComponentsProperties>
            <odeComponentsProperty>
              <key>visibility</key>
              <value>true</value>
            </odeComponentsProperty>
            <odeComponentsProperty>
              <key>teacherOnly</key>
              <value>false</value>
            </odeComponentsProperty>
            <odeComponentsProperty>
              <key>cssClass</key>
              <value></value>
            </odeComponentsProperty>
          </odeComponentsProperties>
        </odeComponent>
      </odeComponents>
    </odePagStructure>
  </odePagStructures>
</odeNavStructure>
<odeNavStructure>
  <odePageId>page-moue5mwh-qljpvllzc</odePageId>
  <odeParentPageId>page-moue5mw8-1179fwth1</odeParentPageId>
  <pageName>Tarea 6</pageName>
  <odeNavStructureOrder>5</odeNavStructureOrder>
  <odeNavStructureProperties>
    <odeNavStructureProperty>
      <key>titlePage</key>
      <value>Tarea 6</value>
    </odeNavStructureProperty>
    <odeNavStructureProperty>
      <key>visibility</key>
      <value>true</value>
    </odeNavStructureProperty>
    <odeNavStructureProperty>
      <key>highlight</key>
      <value>false</value>
    </odeNavStructureProperty>
    <odeNavStructureProperty>
      <key>hidePageTitle</key>
      <value>false</value>
    </odeNavStructureProperty>
    <odeNavStructureProperty>
      <key>editableInPage</key>
      <value>false</value>
    </odeNavStructureProperty>
    <odeNavStructureProperty>
      <key>titlePage</key>
      <value>Tarea 6</value>
    </odeNavStructureProperty>
    <odeNavStructureProperty>
      <key>titleNode</key>
      <value></value>
    </odeNavStructureProperty>
  </odeNavStructureProperties>
  <odePagStructures>
    <odePagStructure>
      <odePageId>page-moue5mwh-qljpvllzc</odePageId>
      <odeBlockId>block-1778091760021-b8wx7ts2h</odeBlockId>
      <blockName>Texto</blockName>
      <iconName></iconName>
      <odePagStructureOrder>1</odePagStructureOrder>
      <odePagStructureProperties>
        <odePagStructureProperty>
          <key>visibility</key>
          <value>true</value>
        </odePagStructureProperty>
        <odePagStructureProperty>
          <key>teacherOnly</key>
          <value>false</value>
        </odePagStructureProperty>
        <odePagStructureProperty>
          <key>allowToggle</key>
          <value>true</value>
        </odePagStructureProperty>
        <odePagStructureProperty>
          <key>minimized</key>
          <value>false</value>
        </odePagStructureProperty>
        <odePagStructureProperty>
          <key>cssClass</key>
          <value></value>
        </odePagStructureProperty>
      </odePagStructureProperties>
      <odeComponents>
        <odeComponent>
          <odePageId>page-moue5mwh-qljpvllzc</odePageId>
          <odeBlockId>block-1778091760021-b8wx7ts2h</odeBlockId>
          <odeIdeviceId>idevice-1778091760019-7pbscyswj</odeIdeviceId>
          <odeIdeviceTypeName>text</odeIdeviceTypeName>
          <htmlView><![CDATA[<div class="exe-text-template">
    <p>Elaboración de nuestro producto final. Recopilación de todos los cuentos creados en formato digital.</p>
<p>Criterios de evaluación: CE2.1 → Produce textos coherentes y estructurados CE2.2 → Aplica ortografía básica (mayúsculas, puntuación) CE3.1 → Participa en intercambios comunicativos CE4.1 → Usa herramientas digitales para crear contenido<a href="asset://7effbd69-9433-217f-c60d-0c648fc2d28a.pdf" title="Recopilación de nuestros cuentos.pdf">asset://7effbd69-9433-217f-c60d-0c648fc2d28a.pdf</a></p>
</div>]]></htmlView>
          <jsonProperties><![CDATA[{"ideviceId":"idevice-1778091760019-7pbscyswj","textInfoDurationInput":"","textInfoDurationTextInput":"Duración","textInfoParticipantsInput":"","textInfoParticipantsTextInput":"Agrupamiento","textTextarea":"<p>Elaboración de nuestro producto final. Recopilación de todos los cuentos creados en formato digital.</p>\n<p>Criterios de evaluación: CE2.1 → Produce textos coherentes y estructurados CE2.2 → Aplica ortografía básica (mayúsculas, puntuación) CE3.1 → Participa en intercambios comunicativos CE4.1 → Usa herramientas digitales para crear contenido<a href=\"asset://7effbd69-9433-217f-c60d-0c648fc2d28a.pdf\" title=\"Recopilación de nuestros cuentos.pdf\">asset://7effbd69-9433-217f-c60d-0c648fc2d28a.pdf</a></p>","textFeedbackInput":"Mostrar retroalimentación","textFeedbackTextarea":""}]]></jsonProperties>
          <odeComponentsOrder>0</odeComponentsOrder>
          <odeComponentsProperties>
            <odeComponentsProperty>
              <key>visibility</key>
              <value>true</value>
            </odeComponentsProperty>
            <odeComponentsProperty>
              <key>teacherOnly</key>
              <value>false</value>
            </odeComponentsProperty>
            <odeComponentsProperty>
              <key>cssClass</key>
              <value></value>
            </odeComponentsProperty>
          </odeComponentsProperties>
        </odeComponent>
      </odeComponents>
    </odePagStructure>
  </odePagStructures>
</odeNavStructure>
<odeNavStructure>
  <odePageId>page-moue5mwi-ka6hu6rkk</odePageId>
  <odeParentPageId></odeParentPageId>
  <pageName>Línea del tiempo</pageName>
  <odeNavStructureOrder>4</odeNavStructureOrder>
  <odeNavStructureProperties>
    <odeNavStructureProperty>
      <key>titlePage</key>
      <value>Línea del tiempo</value>
    </odeNavStructureProperty>
    <odeNavStructureProperty>
      <key>visibility</key>
      <value>true</value>
    </odeNavStructureProperty>
    <odeNavStructureProperty>
      <key>highlight</key>
      <value>false</value>
    </odeNavStructureProperty>
    <odeNavStructureProperty>
      <key>hidePageTitle</key>
      <value>false</value>
    </odeNavStructureProperty>
    <odeNavStructureProperty>
      <key>editableInPage</key>
      <value>false</value>
    </odeNavStructureProperty>
    <odeNavStructureProperty>
      <key>titlePage</key>
      <value>Línea del tiempo</value>
    </odeNavStructureProperty>
    <odeNavStructureProperty>
      <key>titleNode</key>
      <value></value>
    </odeNavStructureProperty>
  </odeNavStructureProperties>
  <odePagStructures>
    <odePagStructure>
      <odePageId>page-moue5mwi-ka6hu6rkk</odePageId>
      <odeBlockId>block-1778092040133-mwn4wvx4j</odeBlockId>
      <blockName>Texto</blockName>
      <iconName></iconName>
      <odePagStructureOrder>1</odePagStructureOrder>
      <odePagStructureProperties>
        <odePagStructureProperty>
          <key>visibility</key>
          <value>true</value>
        </odePagStructureProperty>
        <odePagStructureProperty>
          <key>teacherOnly</key>
          <value>false</value>
        </odePagStructureProperty>
        <odePagStructureProperty>
          <key>allowToggle</key>
          <value>true</value>
        </odePagStructureProperty>
        <odePagStructureProperty>
          <key>minimized</key>
          <value>false</value>
        </odePagStructureProperty>
        <odePagStructureProperty>
          <key>cssClass</key>
          <value></value>
        </odePagStructureProperty>
      </odePagStructureProperties>
      <odeComponents>
        <odeComponent>
          <odePageId>page-moue5mwi-ka6hu6rkk</odePageId>
          <odeBlockId>block-1778092040133-mwn4wvx4j</odeBlockId>
          <odeIdeviceId>idevice-1778092040129-f2005llf7</odeIdeviceId>
          <odeIdeviceTypeName>text</odeIdeviceTypeName>
          <htmlView><![CDATA[<div class="exe-text-template">
    <p><a href="asset://393f20c5-2db6-70e2-a704-b565d6fc8350.pdf" title="línea del tiempo.pdf">asset://393f20c5-2db6-70e2-a704-b565d6fc8350.pdf</a></p>
</div>]]></htmlView>
          <jsonProperties><![CDATA[{"ideviceId":"idevice-1778092040129-f2005llf7","textInfoDurationInput":"","textInfoDurationTextInput":"Duración","textInfoParticipantsInput":"","textInfoParticipantsTextInput":"Agrupamiento","textTextarea":"<p><a href=\"asset://393f20c5-2db6-70e2-a704-b565d6fc8350.pdf\" title=\"línea del tiempo.pdf\">asset://393f20c5-2db6-70e2-a704-b565d6fc8350.pdf</a></p>","textFeedbackInput":"Mostrar retroalimentación","textFeedbackTextarea":""}]]></jsonProperties>
          <odeComponentsOrder>0</odeComponentsOrder>
          <odeComponentsProperties>
            <odeComponentsProperty>
              <key>visibility</key>
              <value>true</value>
            </odeComponentsProperty>
            <odeComponentsProperty>
              <key>teacherOnly</key>
              <value>false</value>
            </odeComponentsProperty>
            <odeComponentsProperty>
              <key>cssClass</key>
              <value></value>
            </odeComponentsProperty>
          </odeComponentsProperties>
        </odeComponent>
      </odeComponents>
    </odePagStructure>
  </odePagStructures>
</odeNavStructure>
<odeNavStructure>
  <odePageId>page-1778092252322-cgq16t8j0</odePageId>
  <odeParentPageId></odeParentPageId>
  <pageName>Evaluación</pageName>
  <odeNavStructureOrder>11</odeNavStructureOrder>
  <odeNavStructureProperties>
    <odeNavStructureProperty>
      <key>titlePage</key>
      <value>Evaluación</value>
    </odeNavStructureProperty>
  </odeNavStructureProperties>
  <odePagStructures>
    <odePagStructure>
      <odePageId>page-1778092252322-cgq16t8j0</odePageId>
      <odeBlockId>block-1778092256049-gn3x27geh</odeBlockId>
      <blockName>Descargar el archivo fuente</blockName>
      <iconName></iconName>
      <odePagStructureOrder>1</odePagStructureOrder>
      <odePagStructureProperties>
        <odePagStructureProperty>
          <key>visibility</key>
          <value>true</value>
        </odePagStructureProperty>
        <odePagStructureProperty>
          <key>teacherOnly</key>
          <value>false</value>
        </odePagStructureProperty>
        <odePagStructureProperty>
          <key>allowToggle</key>
          <value>true</value>
        </odePagStructureProperty>
        <odePagStructureProperty>
          <key>minimized</key>
          <value>false</value>
        </odePagStructureProperty>
        <odePagStructureProperty>
          <key>cssClass</key>
          <value></value>
        </odePagStructureProperty>
      </odePagStructureProperties>
      <odeComponents>
        <odeComponent>
          <odePageId>page-1778092252322-cgq16t8j0</odePageId>
          <odeBlockId>block-1778092256049-gn3x27geh</odeBlockId>
          <odeIdeviceId>idevice-1778092256046-iywk1jgt8</odeIdeviceId>
          <odeIdeviceTypeName>download-source-file</odeIdeviceTypeName>
          <htmlView><![CDATA[<div class="exe-download-package-instructions"><table class="exe-table exe-package-info"><caption title="Rúbrica de evaluación.pdf"><a href="asset://1e19fed6-87eb-3076-7700-0ec91ce20d52.pdf" title="Diana de evaluación.pdf">asset://1e19fed6-87eb-3076-7700-0ec91ce20d52.pdf</a><a href="asset://791f5a83-af37-03d7-9611-95ba0df6e372.pdf" title="Rúbrica de evaluación exposición.pdf">asset://791f5a83-af37-03d7-9611-95ba0df6e372.pdf</a><a href="asset://418227cf-ce60-2ffc-883f-21cbb57a4957.pdf" title="Rúbrica de evaluación.pdf">asset://418227cf-ce60-2ffc-883f-21cbb57a4957.pdf</a>Información general sobre este recurso educativo</caption>
<tbody>
<tr>
<th>Título</th>
<td class="mceNonEditable exe-prop-locked"><span class="exe-prop-title">Proyecto VOCES QUE CUENTAN</span></td>
</tr>
<tr>
<th>Descripción</th>
<td class="mceNonEditable exe-prop-locked"><span class="exe-prop-description">La situación de aprendizaje Voces que cuentan va destinada para el alumnado de 4º curso de Educación Primaria. En la que aprenderemos a conocer y manipular diferentes tipos de textos así como la creación propia de textos.</span></td>
</tr>
<tr>
<th>Autoría</th>
<td class="mceNonEditable exe-prop-locked"><span class="exe-prop-author">Gema María Ortiz López</span></td>
</tr>
<tr>
<th>Licencia</th>
<td class="mceNonEditable exe-prop-locked"><span class="exe-prop-license">creative commons: attribution - share alike 4.0</span></td>
</tr>
</tbody>
</table>
<p style="text-align: center;">Este contenido fue creado con <a href="https://exelearning.net/">eXeLearning</a>, el editor libre y de fuente abierta diseñado para crear recursos educativos.</p></div><p class="exe-download-package-link"><a download="exe-package:elp-name" href="exe-package:elp" style="background-color:#107275;color:#ffffff;">Descargar el archivo .elpx</a></p>]]></htmlView>
          <jsonProperties></jsonProperties>
          <odeComponentsOrder>0</odeComponentsOrder>
          <odeComponentsProperties>
          </odeComponentsProperties>
        </odeComponent>
      </odeComponents>
    </odePagStructure>
  </odePagStructures>
</odeNavStructure>
<odeNavStructure>
  <odePageId>page-1778092548770-5xav9nf19</odePageId>
  <odeParentPageId></odeParentPageId>
  <pageName>Guía didáctica</pageName>
  <odeNavStructureOrder>12</odeNavStructureOrder>
  <odeNavStructureProperties>
    <odeNavStructureProperty>
      <key>titlePage</key>
      <value>Guía didáctica</value>
    </odeNavStructureProperty>
  </odeNavStructureProperties>
  <odePagStructures>
    <odePagStructure>
      <odePageId>page-1778092548770-5xav9nf19</odePageId>
      <odeBlockId>block-1778092552888-zeia3f06d</odeBlockId>
      <blockName>Descargar el archivo fuente</blockName>
      <iconName></iconName>
      <odePagStructureOrder>1</odePagStructureOrder>
      <odePagStructureProperties>
        <odePagStructureProperty>
          <key>visibility</key>
          <value>true</value>
        </odePagStructureProperty>
        <odePagStructureProperty>
          <key>teacherOnly</key>
          <value>false</value>
        </odePagStructureProperty>
        <odePagStructureProperty>
          <key>allowToggle</key>
          <value>true</value>
        </odePagStructureProperty>
        <odePagStructureProperty>
          <key>minimized</key>
          <value>false</value>
        </odePagStructureProperty>
        <odePagStructureProperty>
          <key>cssClass</key>
          <value></value>
        </odePagStructureProperty>
      </odePagStructureProperties>
      <odeComponents>
        <odeComponent>
          <odePageId>page-1778092548770-5xav9nf19</odePageId>
          <odeBlockId>block-1778092552888-zeia3f06d</odeBlockId>
          <odeIdeviceId>idevice-1778092552886-fy66prnng</odeIdeviceId>
          <odeIdeviceTypeName>download-source-file</odeIdeviceTypeName>
          <htmlView><![CDATA[<div class="exe-download-package-instructions"><table class="exe-table exe-package-info"><caption title="Copia de 6.1. Asociamos tareas a Criterios de evaluación - Documentos de Google.pdf"><a href="asset://659ba78e-fcb4-68fe-f8b8-6caab2878b5b.pdf" title="Copia de 6.1. Asociamos tareas a Criterios de evaluación - Documentos de Google.pdf">asset://659ba78e-fcb4-68fe-f8b8-6caab2878b5b.pdf</a>Información general sobre este recurso educativo</caption>
<tbody>
<tr>
<th>Título</th>
<td class="mceNonEditable exe-prop-locked"><span class="exe-prop-title">Proyecto VOCES QUE CUENTAN</span></td>
</tr>
<tr>
<th>Descripción</th>
<td class="mceNonEditable exe-prop-locked"><span class="exe-prop-description">La situación de aprendizaje Voces que cuentan va destinada para el alumnado de 4º curso de Educación Primaria. En la que aprenderemos a conocer y manipular diferentes tipos de textos así como la creación propia de textos.</span></td>
</tr>
<tr>
<th>Autoría</th>
<td class="mceNonEditable exe-prop-locked"><span class="exe-prop-author">Gema María Ortiz López</span></td>
</tr>
<tr>
<th>Licencia</th>
<td class="mceNonEditable exe-prop-locked"><span class="exe-prop-license">creative commons: attribution - share alike 4.0</span></td>
</tr>
</tbody>
</table>
<p style="text-align: center;">Este contenido fue creado con <a href="https://exelearning.net/">eXeLearning</a>, el editor libre y de fuente abierta diseñado para crear recursos educativos.</p></div><p class="exe-download-package-link"><a download="exe-package:elp-name" href="exe-package:elp" style="background-color:#107275;color:#ffffff;">Descargar el archivo .elpx</a></p>]]></htmlView>
          <jsonProperties></jsonProperties>
          <odeComponentsOrder>0</odeComponentsOrder>
          <odeComponentsProperties>
          </odeComponentsProperties>
        </odeComponent>
      </odeComponents>
    </odePagStructure>
  </odePagStructures>
</odeNavStructure>
</odeNavStructures>
</ode>